anyconfig_fit_backend/__init__.py
anyconfig_fit_backend/parser.py
anyconfig_fit_backend-0.1.1.dist-info/LICENSE.MIT
anyconfig_fit_backend-0.1.1.dist-info/METADATA
anyconfig_fit_backend-0.1.1.dist-info/WHEEL
anyconfig_fit_backend-0.1.1.dist-info/entry_points.txt
anyconfig_fit_backend-0.1.1.dist-info/top_level.txt
anyconfig_fit_backend-0.1.1.dist-info/RECORD
