Metadata-Version: 2.1
Name: anyconfig-fit-backend
Version: 0.1.1
Summary: Backend module for python-anyconfig to load FIT data files
Home-page: https://github.com/ssato/python-anyconfig-fit-backend
Author: Satoru SATOH
Author-email: satoru.satoh@gmail.com
Maintainer: Satoru SATOH
Maintainer-email: satoru.satoh@gmail.com
License: MIT
Project-URL: CI: Github Actions, https://github.com/ssato/python-anyconfig-fit-backend/actions
Project-URL: Download, https://pypi.org/project/anyconfig-fit-backend/
Project-URL: Download RPMs, https://copr.fedoraproject.org/coprs/ssato/python-anyconfig/
Project-URL: Bug Tracker, https://github.com/ssato/python-anyconfig-fit-backend/issues
Project-URL: Source, https://github.com/ssato/python-anyconfig-fit-backend
Platform: any
Classifier: Development Status :: 4 - Beta
Classifier: Intended Audience :: Developers
Classifier: Programming Language :: Python
Classifier: Programming Language :: Python :: 3
Classifier: Programming Language :: Python :: 3.6
Classifier: Programming Language :: Python :: 3.7
Classifier: Programming Language :: Python :: 3.8
Classifier: Programming Language :: Python :: 3.9
Classifier: Programming Language :: Python :: 3.10
Classifier: Operating System :: OS Independent
Classifier: Topic :: Software Development :: Libraries :: Python Modules
Classifier: Topic :: Utilities
Classifier: License :: OSI Approved :: MIT License
License-File: LICENSE.MIT
Requires-Dist: anyconfig
